MongoRex/__init__.py
MongoRex/mongorex.py
MongoRex-1.0.3.dist-info/LICENSE
MongoRex-1.0.3.dist-info/METADATA
MongoRex-1.0.3.dist-info/WHEEL
MongoRex-1.0.3.dist-info/top_level.txt
MongoRex-1.0.3.dist-info/RECORD
