Metadata-Version: 2.2
Name: MongoRex
Version: 1.0.3
Summary: MongoRex simplifies MongoDB operations by providing a clean, reusable interface for CRUD, indexing, aggregation, and database management tasks.
Home-page: https://github.com/TraxDinosaur/MongoRex
Author: TraxDinosaur
Keywords: MongoDB,Python MongoDB,MongoDB operations,CRUD operations,Database management,MongoDB Python package,MongoDB CRUD,MongoDB indexing,MongoDB aggregation,Database interface,MongoDB toolkit,Python database library,MongoRex
Classifier: Programming Language :: Python :: 3
Classifier: License :: OSI Approved
Classifier: Operating System :: OS Independent
Requires-Python: >=3.6
License-File: LICENSE
Requires-Dist: pymongo
Dynamic: author
Dynamic: classifier
Dynamic: description
Dynamic: description-content-type
Dynamic: home-page
Dynamic: keywords
Dynamic: requires-dist
Dynamic: requires-python
Dynamic: summary
